asgi_prometheus_exporter/__init__.py
asgi_prometheus_exporter/metrics.py
asgi_prometheus_exporter/middleware.py
asgi_prometheus_exporter-0.1.0.dist-info/METADATA
asgi_prometheus_exporter-0.1.0.dist-info/WHEEL
asgi_prometheus_exporter-0.1.0.dist-info/licenses/LICENSE
asgi_prometheus_exporter-0.1.0.dist-info/RECORD
